fujitsu_automl/__init__.py
fujitsu_automl/anonymize.py
fujitsu_automl/auth.py
fujitsu_automl/escape_util.py
fujitsu_automl/generator.py
fujitsu_automl/params.py
fujitsu_automl/ps_macros.py
fujitsu_automl-3.2.0.dist-info/LICENSE
fujitsu_automl-3.2.0.dist-info/METADATA
fujitsu_automl-3.2.0.dist-info/WHEEL
fujitsu_automl-3.2.0.dist-info/entry_points.txt
fujitsu_automl-3.2.0.dist-info/RECORD
