Metadata-Version: 2.1
Name: fujitsu-automl
Version: 3.2.0
Summary: Fujitsu AutoML API Client for Python
Author: Fujitsu Research, Fujitsu Limited
Requires-Python: >=3.10,<3.13
Classifier: Programming Language :: Python :: 3
Classifier: Programming Language :: Python :: 3.10
Classifier: Programming Language :: Python :: 3.11
Classifier: Programming Language :: Python :: 3.12
Requires-Dist: jsonrpcclient (>=4.0.3,<5.0.0)
Requires-Dist: msal (>=1.23.0,<2.0.0)
Requires-Dist: sapientml
Requires-Dist: sapientml-core
Requires-Dist: toml (>=0.10.2,<0.11.0)
